knorket_tunnel/__init__.py
knorket_tunnel/main.py
knorket_tunnel-0.1.0.dist-info/METADATA
knorket_tunnel-0.1.0.dist-info/WHEEL
knorket_tunnel-0.1.0.dist-info/entry_points.txt
knorket_tunnel-0.1.0.dist-info/top_level.txt
knorket_tunnel-0.1.0.dist-info/RECORD
